b_cfn_twilio/__init__.py
b_cfn_twilio/cfn_activity/__init__.py
b_cfn_twilio/cfn_activity/function.py
b_cfn_twilio/cfn_activity/resource.py
b_cfn_twilio/cfn_activity/twilio_activity.py
b_cfn_twilio/cfn_activity/source/__init__.py
b_cfn_twilio/cfn_activity/source/main/__init__.py
b_cfn_twilio/cfn_activity/source/main/action.py
b_cfn_twilio/cfn_activity/source/main/index.py
b_cfn_twilio/cfn_task_queue/__init__.py
b_cfn_twilio/cfn_task_queue/function.py
b_cfn_twilio/cfn_task_queue/resource.py
b_cfn_twilio/cfn_task_queue/source/__init__.py
b_cfn_twilio/cfn_task_queue/source/main/__init__.py
b_cfn_twilio/cfn_task_queue/source/main/action.py
b_cfn_twilio/cfn_task_queue/source/main/index.py
b_cfn_twilio/cfn_workflow/__init__.py
b_cfn_twilio/cfn_workflow/function.py
b_cfn_twilio/cfn_workflow/resource.py
b_cfn_twilio/cfn_workflow/source/__init__.py
b_cfn_twilio/cfn_workflow/source/main/__init__.py
b_cfn_twilio/cfn_workflow/source/main/action.py
b_cfn_twilio/cfn_workflow/source/main/index.py
b_cfn_twilio/cfn_workspace/__init__.py
b_cfn_twilio/cfn_workspace/function.py
b_cfn_twilio/cfn_workspace/resource.py
b_cfn_twilio/cfn_workspace/source/__init__.py
b_cfn_twilio/cfn_workspace/source/main/__init__.py
b_cfn_twilio/cfn_workspace/source/main/action.py
b_cfn_twilio/cfn_workspace/source/main/index.py
b_cfn_twilio-1.0.0.dist-info/LICENSE
b_cfn_twilio-1.0.0.dist-info/METADATA
b_cfn_twilio-1.0.0.dist-info/WHEEL
b_cfn_twilio-1.0.0.dist-info/top_level.txt
b_cfn_twilio-1.0.0.dist-info/RECORD
