Metadata-Version: 2.1
Name: b-cfn-twilio
Version: 1.0.0
Summary: A collection of AWS CDK based twilio resources.
Home-page: https://github.com/biomapas/B.CfnTwilio.git
Author: Robertas Stankevičius
Author-email: robertas.stankevicius@biomapas.com
License: Apache License 2.0
Keywords: AWS CDK Lambda CloudFormation Twilio
Platform: UNKNOWN
Classifier: Programming Language :: Python :: 3
Classifier: Operating System :: OS Independent
Requires-Dist: aws-cdk.core (<2.0.0,>=1.54.0)
Requires-Dist: aws-cdk.aws-lambda (<2.0.0,>=1.54.0)
Requires-Dist: twilio (<7.0.0,>=6.44.0)
Requires-Dist: b-twilio-sdk-layer (<2.0.0,>=1.0.0)
Requires-Dist: b-aws-cf-response (<1.0.0,>=0.0.2)
